{
  "companies": [
    {"short": "SAIROGULLARI", "name": "SAIROGULLARI DIS TICARET LTD STI",
     "address": "OYMAAGAC MAH. 5062 CAD, KAYSERI / TURKEY", "tax_no": "",
     "phone": "+90 541 924 98 70", "email": "talat@sairogullari.com",
     "bank_name": "Türkiye İş Bankası A.Ş.", "branch": "Kayseri O.S.B.", "branch_code": "4000",
     "iban": "TR26 0006 4000 0025 3060 0556 24", "swift": "ISBKTRIS"},

    {"short": "TLT", "name": "TLT ÇELİK KAPI MOBİLYA SANAYİ VE TİCARET LİMİTED ŞİRKETİ",
     "address": "CAMİKEBİR MAH. 5062. CAD. 1. BLOK NO: 3 E, KOCASINAN / KAYSERI, TURKEY · Vergi D.: GEVHER NESİBE VD.",
     "tax_no": "1550986460", "phone": "", "email": "",
     "bank_name": "", "branch": "", "branch_code": "", "iban": "", "swift": ""},

    {"short": "RANGE", "name": "RANGE İÇ VE DIŞ TİCARET LİMİTED ŞİRKETİ",
     "address": "BAHÇELİEVLER MAH. GARİPSU İŞYERLERİ KÜME EVLERİ NO: 196, İNCESU / KAYSERI, TURKEY · Vergi D.: İNCESU MAL MÜDÜRLÜĞÜ",
     "tax_no": "7341049642", "phone": "+90 352 504 09 09", "email": "muhasebe3@realsteeldoor.com",
     "bank_name": "VAKIFBANK (TURKEY)", "branch": "KAYSERİ ORGANİZE SANAYİ ŞUBESİ", "branch_code": "",
     "iban": "", "swift": "TVBATR2A"},

    {"short": "NEWA GROUP", "name": "NEWA GROUP METARALUJİ İTHALAT İHRACAAT SANAYİ VE TİCARET LİMİTED ŞİRKETİ",
     "address": "GEVHER NESİBE MAH. MENEKŞE SK. NO:2/A, KOCASİNAN, KAYSERİ, TURKEY",
     "tax_no": "6311984807", "phone": "+90 352 504 09 09", "email": "info@akvasteeldoor.com",
     "account_no": "00158048017458915",
     "bank_name": "VAKIFBANK (TURKEY)", "branch": "KAYSERİ ORGANİZE SANAYİ ŞUBESİ", "branch_code": "",
     "iban": "TR85 0001 5001 5804 8024 6255 65", "swift": "TVBATR2A"},

    {"short": "MFY", "name": "MFY",
     "address": "ORGANİZE SANAYİ BÖLGESİ 47. CAD. NO:07, PK:38070, MELİKGAZİ / KAYSERİ / TURKEY",
     "tax_no": "6201224588", "phone": "+90 352 504 09 09", "email": "",
     "bank_name": "", "branch": "", "branch_code": "", "iban": "", "swift": ""}
  ],
  "customers": [
    {"name": "سعد زكي — Modern Style (مصر)", "contact": "SAAD ZAKY FAHIM ABDELSAYED",
     "address": "99 Mostafa El-Nahhas St, Nasr City, 8th District, Cairo, Egypt",
     "phone": "+20 121 116 4530", "tax_no": "741496100", "country": "Egypt", "currency": "EGP",
     "email": "", "acid": "ACID7414961001010310017"},
    {"name": "محمود — الأردن", "country": "Jordan", "currency": "JOD"},
    {"name": "علي الجبوري — العراق", "country": "Iraq", "currency": "IQD"},
    {"name": "مينا — مصر", "country": "Egypt", "currency": "EGP"},
    {"name": "بيت سلطان", "country": "", "currency": "USD"},
    {"name": "عمرو إبراهيم — مصر", "country": "Egypt", "currency": "EGP"},
    {"name": "محمود — ليبيا", "country": "Libya", "currency": "LYD"},
    {"name": "عصام — فلسطين", "country": "Palestine", "currency": "USD"},
    {"name": "التشادي", "country": "Chad", "currency": "USD"},
    {"name": "ياسر مرسي — مصر", "contact": "YASSER MOURSİ", "country": "Egypt", "currency": "EGP"},
    {"name": "محمد نعمة", "country": "Turkey", "currency": "USD"},
    {"name": "محمد — الأردن", "country": "Jordan", "currency": "JOD"},
    {"name": "إيمان السيد — مصر", "country": "Egypt", "currency": "EGP"},
    {"name": "الحرام — صلاح", "country": "", "currency": "USD"},
    {"name": "صلاح الشيخ — مصر", "country": "Egypt", "currency": "EGP"},
    {"name": "السعودي — علي العراق", "country": "Iraq", "currency": "IQD"},
    {"name": "عبدالله — مصر", "country": "Egypt", "currency": "EGP"},
    {"name": "Elite Door (إيليت)", "country": "", "currency": "USD"},
    {"name": "Tetra Door (تيترا)", "country": "", "currency": "USD"},
    {"name": "Strong (سترونج)", "country": "", "currency": "USD"},
    {"name": "STE (إس تي إي)", "country": "", "currency": "USD"}
  ]
}
